shove/__init__.py
shove/_compat.py
shove/_imports.py
shove/base.py
shove/cache.py
shove/core.py
shove/store.py
shove/test/__init__.py
shove/test/mixins.py
shove/test/test_cache.py
shove/test/test_multishove.py
shove/test/test_store.py
shove-0.6.6.dist-info/DESCRIPTION.rst
shove-0.6.6.dist-info/METADATA
shove-0.6.6.dist-info/RECORD
shove-0.6.6.dist-info/WHEEL
shove-0.6.6.dist-info/entry_points.txt
shove-0.6.6.dist-info/metadata.json
shove-0.6.6.dist-info/pbr.json
shove-0.6.6.dist-info/top_level.txt
