Metadata-Version: 2.0
Name: shove
Version: 0.6.6
Summary: Generic dictionaryish object storage frontend
Home-page: https://bitbucket.org/lcrees/shove/
Author: L. C. Rees
Author-email: lcrees@gmail.com
License: BSD
Keywords: object storage persistence database dictionary
Platform: UNKNOWN
Classifier: Development Status :: 4 - Beta
Classifier: License :: OSI Approved :: BSD License
Classifier: Operating System :: OS Independent
Classifier: Programming Language :: Python
Classifier: Topic :: Database :: Front-Ends
Classifier: Topic :: Software Development :: Libraries
Classifier: Programming Language :: Python
Classifier: Programming Language :: Python :: 2
Classifier: Programming Language :: Python :: 2.6
Classifier: Programming Language :: Python :: 2.7
Classifier: Programming Language :: Python :: 3.2
Classifier: Programming Language :: Python :: 3
Classifier: Programming Language :: Python :: 3.3
Classifier: Programming Language :: Python :: 3.4
Classifier: Programming Language :: Python :: 3.5
Classifier: Programming Language :: Python :: Implementation :: PyPy
Classifier: Programming Language :: Python :: Implementation :: CPython
Classifier: Framework :: Setuptools Plugin
Requires-Dist: futures
Requires-Dist: setuptools
Requires-Dist: stuf (>=0.9.14)
